olympix_test_generator/__init__.py
olympix_test_generator/client.py
olympix_test_generator-1.2.2.dist-info/METADATA
olympix_test_generator-1.2.2.dist-info/WHEEL
olympix_test_generator-1.2.2.dist-info/entry_points.txt
olympix_test_generator-1.2.2.dist-info/top_level.txt
olympix_test_generator-1.2.2.dist-info/RECORD
