Metadata-Version: 2.1
Name: olympix-test-generator
Version: 1.2.2
Summary: Used to auto-generate unit tests for smart contracts using the Forge framework.
Home-page: https://github.com/olympix/olympix-test-generator
Author: Evan Fenster
Author-email: evan@olympix.ai
Classifier: License :: OSI Approved :: MIT License
Classifier: Programming Language :: Python :: 3
Classifier: Programming Language :: Python :: 3.7
Classifier: Programming Language :: Python :: 3.8
Classifier: Programming Language :: Python :: 3.9
Requires-Dist: blessed (==1.20.0)
Requires-Dist: certifi (==2023.5.7)
Requires-Dist: charset-normalizer (==3.2.0)
Requires-Dist: idna (==3.4)
Requires-Dist: inquirer (==3.1.3)
Requires-Dist: python-dotenv (==1.0.0)
Requires-Dist: python-editor (==1.0.4)
Requires-Dist: readchar (==4.0.5)
Requires-Dist: requests (==2.31.0)
Requires-Dist: six (==1.16.0)
Requires-Dist: urllib3 (==2.0.4)
Requires-Dist: wcwidth (==0.2.6)
